setup.py
django_redirection/__init__.py
django_redirection/models.py
django_redirection/tests.py
django_redirection/urls.py
django_redirection/views.py
django_redirection.egg-info/PKG-INFO
django_redirection.egg-info/SOURCES.txt
django_redirection.egg-info/dependency_links.txt
django_redirection.egg-info/entry_points.txt
django_redirection.egg-info/not-zip-safe
django_redirection.egg-info/top_level.txt