Metadata-Version: 1.1
Name: django-redirection
Version: 0.2.1
Summary: Redirection app by using X-Accel-Redirect
Home-page: https://www.whiteblack-cat.info/
Author: ccat
Author-email: UNKNOWN
License: MIT
Platform: UNKNOWN
Classifier: Framework :: Django
Classifier: License :: OSI Approved :: MIT License
Classifier: Programming Language :: Python
